optimizely/__init__.py
optimizely/bucketer.py
optimizely/config_manager.py
optimizely/decision_service.py
optimizely/entities.py
optimizely/error_handler.py
optimizely/event_builder.py
optimizely/event_dispatcher.py
optimizely/exceptions.py
optimizely/logger.py
optimizely/notification_center.py
optimizely/notification_center_registry.py
optimizely/optimizely.py
optimizely/optimizely_config.py
optimizely/optimizely_factory.py
optimizely/optimizely_user_context.py
optimizely/project_config.py
optimizely/user_profile.py
optimizely/version.py
optimizely/cmab/__init__.py
optimizely/cmab/cmab_client.py
optimizely/cmab/cmab_service.py
optimizely/decision/__init__.py
optimizely/decision/optimizely_decide_option.py
optimizely/decision/optimizely_decision.py
optimizely/decision/optimizely_decision_message.py
optimizely/event/__init__.py
optimizely/event/event_factory.py
optimizely/event/event_processor.py
optimizely/event/log_event.py
optimizely/event/payload.py
optimizely/event/user_event.py
optimizely/event/user_event_factory.py
optimizely/helpers/__init__.py
optimizely/helpers/audience.py
optimizely/helpers/condition.py
optimizely/helpers/condition_tree_evaluator.py
optimizely/helpers/constants.py
optimizely/helpers/enums.py
optimizely/helpers/event_tag_utils.py
optimizely/helpers/experiment.py
optimizely/helpers/sdk_settings.py
optimizely/helpers/types.py
optimizely/helpers/validator.py
optimizely/lib/__init__.py
optimizely/lib/pymmh3.py
optimizely/odp/__init__.py
optimizely/odp/lru_cache.py
optimizely/odp/odp_config.py
optimizely/odp/odp_event.py
optimizely/odp/odp_event_api_manager.py
optimizely/odp/odp_event_manager.py
optimizely/odp/odp_manager.py
optimizely/odp/odp_segment_api_manager.py
optimizely/odp/odp_segment_manager.py
optimizely/odp/optimizely_odp_option.py
tests/helpers_tests/__init__.py
tests/helpers_tests/test_audience.py
tests/helpers_tests/test_condition.py
tests/helpers_tests/test_condition_tree_evaluator.py
tests/helpers_tests/test_event_tag_utils.py
optimizely_sdk-5.4.0.dist-info/LICENSE
optimizely_sdk-5.4.0.dist-info/METADATA
optimizely_sdk-5.4.0.dist-info/WHEEL
optimizely_sdk-5.4.0.dist-info/top_level.txt
optimizely_sdk-5.4.0.dist-info/RECORD
