Metadata-Version: 2.1
Name: optimizely-sdk
Version: 5.4.0
Summary: Python SDK for Optimizely Feature Experimentation, Optimizely Full Stack (legacy), and Optimizely Rollouts.
Home-page: https://github.com/optimizely/python-sdk
Author: Optimizely
Author-email: developers@optimizely.com
Classifier: Development Status :: 5 - Production/Stable
Classifier: Environment :: Web Environment
Classifier: Intended Audience :: Developers
Classifier: License :: OSI Approved :: Apache Software License
Classifier: Operating System :: OS Independent
Classifier: Programming Language :: Python
Classifier: Programming Language :: Python :: 3.8
Classifier: Programming Language :: Python :: 3.9
Classifier: Programming Language :: Python :: 3.10
Classifier: Programming Language :: Python :: 3.11
Classifier: Programming Language :: Python :: 3.12
License-File: LICENSE
Requires-Dist: jsonschema>=3.2.0
Requires-Dist: pyrsistent>=0.16.0
Requires-Dist: requests>=2.21
Requires-Dist: idna>=2.10
Requires-Dist: rpds-py<0.20.0; python_version < "3.11"
Provides-Extra: test
Requires-Dist: coverage; extra == "test"
Requires-Dist: pyrsistent>=0.16.0; extra == "test"
Requires-Dist: idna>=2.10; extra == "test"
Requires-Dist: pytest>=6.2.0; extra == "test"
Requires-Dist: pytest-cov; extra == "test"
Requires-Dist: funcsigs>=0.4; extra == "test"
Requires-Dist: requests>=2.21; extra == "test"
Requires-Dist: python-coveralls; extra == "test"
Requires-Dist: jsonschema>=3.2.0; extra == "test"
Requires-Dist: flake8>=4.0.1; extra == "test"
Requires-Dist: rpds-py<0.20.0; python_version < "3.11" and extra == "test"
